{
    "veteranen": [
        {
            "pos": 1,
            "team": "KORBEEK SPORTKORBEEK SPORT",
            "pnt": 46,
            "played": 17,
            "won": 15,
            "draw": 1,
            "lost": 1,
            "goals_for": 56,
            "goals_against": 14,
            "saldo": 42
        },
        {
            "pos": 2,
            "team": "K.V.C. KESSEL LO 2000K.V.C. KESSEL LO 2000",
            "pnt": 38,
            "played": 15,
            "won": 12,
            "draw": 1,
            "lost": 2,
            "goals_for": 82,
            "goals_against": 8,
            "saldo": 74
        },
        {
            "pos": 2,
            "team": "STORMVOGELS HAASRODESTORMVOGELS HAASRODE",
            "pnt": 38,
            "played": 16,
            "won": 12,
            "draw": 2,
            "lost": 2,
            "goals_for": 66,
            "goals_against": 28,
            "saldo": 38
        },
        {
            "pos": 4,
            "team": "ALPIA TILDONKALPIA TILDONK",
            "pnt": 35,
            "played": 17,
            "won": 11,
            "draw": 4,
            "lost": 2,
            "goals_for": 56,
            "goals_against": 34,
            "saldo": 22
        },
        {
            "pos": 5,
            "team": "K.F.C. RAPIDE WEZEMAALK.F.C. RAPIDE WEZEMAAL",
            "pnt": 33,
            "played": 17,
            "won": 10,
            "draw": 4,
            "lost": 3,
            "goals_for": 51,
            "goals_against": 36,
            "saldo": 15
        },
        {
            "pos": 6,
            "team": "VK WAKKERZEELVK WAKKERZEEL",
            "pnt": 29,
            "played": 18,
            "won": 9,
            "draw": 7,
            "lost": 2,
            "goals_for": 30,
            "goals_against": 24,
            "saldo": 6
        },
        {
            "pos": 7,
            "team": "SPORTIEF ROTSELAARSPORTIEF ROTSELAAR",
            "pnt": 27,
            "played": 17,
            "won": 8,
            "draw": 6,
            "lost": 3,
            "goals_for": 53,
            "goals_against": 41,
            "saldo": 12
        },
        {
            "pos": 8,
            "team": "REMY BOYS WIJGMAALREMY BOYS WIJGMAAL",
            "pnt": 25,
            "played": 17,
            "won": 7,
            "draw": 6,
            "lost": 4,
            "goals_for": 39,
            "goals_against": 31,
            "saldo": 8
        },
        {
            "pos": 9,
            "team": "DARING LEUVENDARING LEUVEN",
            "pnt": 22,
            "played": 16,
            "won": 7,
            "draw": 8,
            "lost": 1,
            "goals_for": 39,
            "goals_against": 41,
            "saldo": -2
        },
        {
            "pos": 10,
            "team": "V.C. BERTEM-LEEFDAAL BV.C. BERTEM-LEEFDAAL B",
            "pnt": 16,
            "played": 16,
            "won": 5,
            "draw": 10,
            "lost": 1,
            "goals_for": 31,
            "goals_against": 60,
            "saldo": -29
        },
        {
            "pos": 11,
            "team": "F.C. TABOR HEVERLEE VZWF.C. TABOR HEVERLEE VZW",
            "pnt": 14,
            "played": 15,
            "won": 4,
            "draw": 9,
            "lost": 2,
            "goals_for": 20,
            "goals_against": 39,
            "saldo": -19
        },
        {
            "pos": 12,
            "team": "V.C. BERTEM-LEEFDAAL AV.C. BERTEM-LEEFDAAL A",
            "pnt": 13,
            "played": 18,
            "won": 4,
            "draw": 13,
            "lost": 1,
            "goals_for": 32,
            "goals_against": 66,
            "saldo": -34
        },
        {
            "pos": 12,
            "team": "V.V.S ROTSELAARV.V.S ROTSELAAR",
            "pnt": 13,
            "played": 16,
            "won": 4,
            "draw": 11,
            "lost": 1,
            "goals_for": 18,
            "goals_against": 52,
            "saldo": -34
        },
        {
            "pos": 14,
            "team": "VK ONDER ONS OHR VALVK ONDER ONS OHR VAL",
            "pnt": 13,
            "played": 18,
            "won": 3,
            "draw": 11,
            "lost": 4,
            "goals_for": 30,
            "goals_against": 56,
            "saldo": -26
        },
        {
            "pos": 15,
            "team": "ST JORIS WEERT AST JORIS WEERT A",
            "pnt": 9,
            "played": 15,
            "won": 2,
            "draw": 10,
            "lost": 3,
            "goals_for": 18,
            "goals_against": 45,
            "saldo": -27
        },
        {
            "pos": 16,
            "team": "ST JORIS WEERT BST JORIS WEERT B",
            "pnt": 3,
            "played": 12,
            "won": 1,
            "draw": 11,
            "lost": 0,
            "goals_for": 13,
            "goals_against": 59,
            "saldo": -46
        }
    ],
    "zaterdag": [
        {
            "pos": 1,
            "team": "PERK STEENOKKERZEEL VERENIGD 1820PERK STEENOKKERZEEL VERENIGD 1820",
            "pnt": 38,
            "played": 16,
            "won": 12,
            "draw": 2,
            "lost": 2,
            "goals_for": 60,
            "goals_against": 13,
            "saldo": 47
        },
        {
            "pos": 2,
            "team": "BUFFALO TIENENBUFFALO TIENEN",
            "pnt": 26,
            "played": 13,
            "won": 8,
            "draw": 3,
            "lost": 2,
            "goals_for": 40,
            "goals_against": 32,
            "saldo": 8
        },
        {
            "pos": 3,
            "team": "DE VENNE AARSCHOT BDE VENNE AARSCHOT B",
            "pnt": 25,
            "played": 14,
            "won": 7,
            "draw": 3,
            "lost": 4,
            "goals_for": 48,
            "goals_against": 32,
            "saldo": 16
        },
        {
            "pos": 4,
            "team": "TOEKOMST BUNSBEEKTOEKOMST BUNSBEEK",
            "pnt": 22,
            "played": 13,
            "won": 7,
            "draw": 5,
            "lost": 1,
            "goals_for": 45,
            "goals_against": 48,
            "saldo": -3
        },
        {
            "pos": 5,
            "team": "FC MASSIS ZAVENTEMFC MASSIS ZAVENTEM",
            "pnt": 18,
            "played": 13,
            "won": 5,
            "draw": 5,
            "lost": 3,
            "goals_for": 36,
            "goals_against": 33,
            "saldo": 3
        },
        {
            "pos": 5,
            "team": "R.C. MELDERT BR.C. MELDERT B",
            "pnt": 18,
            "played": 14,
            "won": 5,
            "draw": 6,
            "lost": 3,
            "goals_for": 27,
            "goals_against": 39,
            "saldo": -12
        },
        {
            "pos": 7,
            "team": "REMY BOYS WIJGMAAL BREMY BOYS WIJGMAAL B",
            "pnt": 16,
            "played": 13,
            "won": 5,
            "draw": 7,
            "lost": 1,
            "goals_for": 26,
            "goals_against": 32,
            "saldo": -6
        },
        {
            "pos": 8,
            "team": "ALPIA TILDONKALPIA TILDONK",
            "pnt": 15,
            "played": 16,
            "won": 4,
            "draw": 9,
            "lost": 3,
            "goals_for": 30,
            "goals_against": 53,
            "saldo": -23
        },
        {
            "pos": 9,
            "team": "V.V.S ROTSELAARV.V.S ROTSELAAR",
            "pnt": 13,
            "played": 14,
            "won": 4,
            "draw": 9,
            "lost": 1,
            "goals_for": 36,
            "goals_against": 50,
            "saldo": -14
        },
        {
            "pos": 10,
            "team": "KNEPPER LEEFDAAL BKNEPPER LEEFDAAL B",
            "pnt": 9,
            "played": 14,
            "won": 3,
            "draw": 11,
            "lost": 0,
            "goals_for": 26,
            "goals_against": 42,
            "saldo": -16
        }
    ],
    "zondag": [
        {
            "pos": 1,
            "team": "VK WAKKERZEELVK WAKKERZEEL",
            "pnt": 31,
            "played": 13,
            "won": 10,
            "draw": 2,
            "lost": 1,
            "goals_for": 40,
            "goals_against": 21,
            "saldo": 19
        },
        {
            "pos": 2,
            "team": "K.F.C. WERCHTERK.F.C. WERCHTER",
            "pnt": 30,
            "played": 14,
            "won": 9,
            "draw": 2,
            "lost": 3,
            "goals_for": 42,
            "goals_against": 17,
            "saldo": 25
        },
        {
            "pos": 3,
            "team": "V.V.S ROTSELAARV.V.S ROTSELAAR",
            "pnt": 27,
            "played": 13,
            "won": 8,
            "draw": 2,
            "lost": 3,
            "goals_for": 39,
            "goals_against": 13,
            "saldo": 26
        },
        {
            "pos": 4,
            "team": "V.K. EENDR. EIZERV.K. EENDR. EIZER",
            "pnt": 25,
            "played": 14,
            "won": 7,
            "draw": 3,
            "lost": 4,
            "goals_for": 40,
            "goals_against": 13,
            "saldo": 27
        },
        {
            "pos": 5,
            "team": "SPARTA MELSBROEKSPARTA MELSBROEK",
            "pnt": 23,
            "played": 14,
            "won": 7,
            "draw": 5,
            "lost": 2,
            "goals_for": 53,
            "goals_against": 29,
            "saldo": 24
        },
        {
            "pos": 6,
            "team": "KONINKLIJKE HAACHT UNITEDKONINKLIJKE HAACHT UNITED",
            "pnt": 22,
            "played": 14,
            "won": 7,
            "draw": 6,
            "lost": 1,
            "goals_for": 40,
            "goals_against": 22,
            "saldo": 18
        },
        {
            "pos": 7,
            "team": "K.F.C. HERENTK.F.C. HERENT",
            "pnt": 9,
            "played": 14,
            "won": 3,
            "draw": 11,
            "lost": 0,
            "goals_for": 14,
            "goals_against": 69,
            "saldo": -55
        },
        {
            "pos": 8,
            "team": "FC VILV HEVERLEEFC VILV HEVERLEE",
            "pnt": 8,
            "played": 14,
            "won": 2,
            "draw": 10,
            "lost": 2,
            "goals_for": 21,
            "goals_against": 40,
            "saldo": -19
        },
        {
            "pos": 9,
            "team": "K.N.V.L.H. KEERBERGENK.N.V.L.H. KEERBERGEN",
            "pnt": 0,
            "played": 14,
            "won": 0,
            "draw": 14,
            "lost": 0,
            "goals_for": 5,
            "goals_against": 80,
            "saldo": -75
        }
    ]
}